blend_my_bot/__init__.py
blend_my_bot/blender_model.py
blend_my_bot/link.py
blend_my_bot/model_importer.py
blend_my_bot-1.1.0.dist-info/LICENSE
blend_my_bot-1.1.0.dist-info/METADATA
blend_my_bot-1.1.0.dist-info/WHEEL
blend_my_bot-1.1.0.dist-info/top_level.txt
blend_my_bot-1.1.0.dist-info/RECORD
