Metadata-Version: 2.1
Name: blend-my-bot
Version: 1.1.0
Summary: A package to import URDF files into Blender
Author: "Giuseppe L'Erario"
Author-email: gl.giuseppelerario@gmail.com
Keywords: robotics,blender,animation
Requires-Python: >=3.10
License-File: LICENSE
Requires-Dist: idyntree
Requires-Dist: numpy
Requires-Dist: bpy
